{"_type":"export","__export_format":4,"__export_date":"2021-10-20T12:51:40.419Z","__export_source":"insomnia.desktop.app:v2021.5.3","resources":[{"_id":"req_fae6e9b09a9e4dbba6a295fd10271bb7","parentId":"fld_a98e26bc3e21444fbba161666ab4abd5","modified":1634722446131,"created":1634722438117,"url":"localhost:3001/","name":"Alive","description":"","method":"GET","body":{},"parameters":[],"headers":[],"authentication":{},"metaSortKey":-1634722438117,"isPrivate":false,"settingStoreCookies":true,"settingSendCookies":true,"settingDisableRenderRequestBody":false,"settingEncodeUrl":true,"settingRebuildPath":true,"settingFollowRedirects":"global","_type":"request"},{"_id":"fld_a98e26bc3e21444fbba161666ab4abd5","parentId":"wrk_97ceffbac6e14947b5bd6594b0364760","modified":1634722427057,"created":1634722427057,"name":"API_USER","description":"","environment":{},"environmentPropertyOrder":null,"metaSortKey":-1634722427057,"_type":"request_group"},{"_id":"wrk_97ceffbac6e14947b5bd6594b0364760","parentId":null,"modified":1634107657249,"created":1634107657249,"name":"API med mongo.yaml","description":"","scope":"design","_type":"workspace"},{"_id":"req_97fa4cec09e247519f50bffd4390a5c7","parentId":"fld_a98e26bc3e21444fbba161666ab4abd5","modified":1634728456281,"created":1634722488012,"url":"localhost:3001/users","name":"createUser","description":"","method":"POST","body":{"mimeType":"application/json","text":"{\n\t\"name\": \"Adam\",\n  \"age\": 19,\n  \"gender\": \"Male\"\n}"},"parameters":[],"headers":[{"name":"Content-Type","value":"application/json","id":"pair_bb0aaac5111447e8b47778e9fc10b736"}],"authentication":{},"metaSortKey":-1634415060795,"isPrivate":false,"settingStoreCookies":true,"settingSendCookies":true,"settingDisableRenderRequestBody":false,"settingEncodeUrl":true,"settingRebuildPath":true,"settingFollowRedirects":"global","_type":"request"},{"_id":"req_72a5f625dd7743ac952225b8b366ceeb","parentId":"fld_a98e26bc3e21444fbba161666ab4abd5","modified":1634728795249,"created":1634728787643,"url":"localhost:3001/users","name":"getAllUsers","description":"","method":"GET","body":{},"parameters":[],"headers":[],"authentication":{},"metaSortKey":-1634261372134,"isPrivate":false,"settingStoreCookies":true,"settingSendCookies":true,"settingDisableRenderRequestBody":false,"settingEncodeUrl":true,"settingRebuildPath":true,"settingFollowRedirects":"global","_type":"request"},{"_id":"req_b501a0470b7c4f3489f6a6a35e0ce3d1","parentId":"fld_a98e26bc3e21444fbba161666ab4abd5","modified":1634732748564,"created":1634729319000,"url":"localhost:3001/users/61700a990a67e222481ef00e","name":"getUserWithId","description":"","method":"GET","body":{},"parameters":[],"headers":[],"authentication":{},"metaSortKey":-1634184527803.5,"isPrivate":false,"settingStoreCookies":true,"settingSendCookies":true,"settingDisableRenderRequestBody":false,"settingEncodeUrl":true,"settingRebuildPath":true,"settingFollowRedirects":"global","_type":"request"},{"_id":"req_e670f8d7792443099f4da78198d22d62","parentId":"fld_a98e26bc3e21444fbba161666ab4abd5","modified":1634730081372,"created":1634729942270,"url":"localhost:3001/searchUser?name=Adamm","name":"getUserByName","description":"","method":"GET","body":{},"parameters":[],"headers":[],"authentication":{},"metaSortKey":-1634146105638.25,"isPrivate":false,"settingStoreCookies":true,"settingSendCookies":true,"settingDisableRenderRequestBody":false,"settingEncodeUrl":true,"settingRebuildPath":true,"settingFollowRedirects":"global","_type":"request"},{"_id":"req_e087d50f98ca475dac14711a01aaa972","parentId":"fld_a98e26bc3e21444fbba161666ab4abd5","modified":1634731033586,"created":1634730959842,"url":"localhost:3001/users/6170004070711c4c1fb152c6","name":"updateUser","description":"","method":"PUT","body":{"mimeType":"application/json","text":"{\n\t\"name\": \"Emilie\",\n  \"age\": 24,\n  \"gender\": \"Female\"\n}"},"parameters":[],"headers":[{"name":"Content-Type","value":"application/json","id":"pair_b371e64d59b04c8e97183f11d36f19f8"}],"authentication":{},"metaSortKey":-1634146105588.25,"isPrivate":false,"settingStoreCookies":true,"settingSendCookies":true,"settingDisableRenderRequestBody":false,"settingEncodeUrl":true,"settingRebuildPath":true,"settingFollowRedirects":"global","_type":"request"},{"_id":"req_0ff49413b3524e14a8e13853d9690df4","parentId":"fld_a98e26bc3e21444fbba161666ab4abd5","modified":1634732717341,"created":1634732661659,"url":"localhost:3001/users/61700a990a67e222481ef00e","name":"deleteUserWithId","description":"","method":"DELETE","body":{},"parameters":[],"headers":[],"authentication":{},"metaSortKey":-1634146105538.25,"isPrivate":false,"settingStoreCookies":true,"settingSendCookies":true,"settingDisableRenderRequestBody":false,"settingEncodeUrl":true,"settingRebuildPath":true,"settingFollowRedirects":"global","_type":"request"},{"_id":"req_a1eee84f471f49668804fcdd174618b7","parentId":"fld_7dc0153ddc07455bb929080a1da58403","modified":1634722473713,"created":1634107715159,"url":"localhost:3001/","name":"Alive","description":"","method":"GET","body":{},"parameters":[],"headers":[],"authentication":{},"metaSortKey":-1634107683473,"isPrivate":false,"settingStoreCookies":true,"settingSendCookies":true,"settingDisableRenderRequestBody":false,"settingEncodeUrl":true,"settingRebuildPath":true,"settingFollowRedirects":"global","_type":"request"},{"_id":"fld_7dc0153ddc07455bb929080a1da58403","parentId":"wrk_97ceffbac6e14947b5bd6594b0364760","modified":1634107668922,"created":1634107668922,"name":"Users","description":"","environment":{},"environmentPropertyOrder":null,"metaSortKey":-1634107668922,"_type":"request_group"},{"_id":"req_dc7c88f09f974cbab24aef20b2f5332c","parentId":"fld_7dc0153ddc07455bb929080a1da58403","modified":1634148582440,"created":1634148567142,"url":"localhost:3001/users","name":"getAllUsers","description":"","method":"GET","body":{},"parameters":[],"headers":[],"authentication":{},"metaSortKey":-1634107683423,"isPrivate":false,"settingStoreCookies":true,"settingSendCookies":true,"settingDisableRenderRequestBody":false,"settingEncodeUrl":true,"settingRebuildPath":true,"settingFollowRedirects":"global","_type":"request"},{"_id":"req_54205fe59d9647478a4524f486009615","parentId":"fld_7dc0153ddc07455bb929080a1da58403","modified":1634149093157,"created":1634149049196,"url":"localhost:3001/users/616718bda4ab77e25e33ec5b","name":"getUserWithId","description":"","method":"GET","body":{},"parameters":[],"headers":[],"authentication":{},"metaSortKey":-1634107683398,"isPrivate":false,"settingStoreCookies":true,"settingSendCookies":true,"settingDisableRenderRequestBody":false,"settingEncodeUrl":true,"settingRebuildPath":true,"settingFollowRedirects":"global","_type":"request"},{"_id":"req_e284072e1d4e4827a51656c420282ac2","parentId":"fld_7dc0153ddc07455bb929080a1da58403","modified":1634150638759,"created":1634149974594,"url":"localhost:3001/searchUser?username=Adam","name":"getUserWithQuery","description":"","method":"GET","body":{},"parameters":[],"headers":[],"authentication":{},"metaSortKey":-1634107683385.5,"isPrivate":false,"settingStoreCookies":true,"settingSendCookies":true,"settingDisableRenderRequestBody":false,"settingEncodeUrl":true,"settingRebuildPath":true,"settingFollowRedirects":"global","_type":"request"},{"_id":"req_335112af2c7f4f4f8bd018e7e4b73b35","parentId":"fld_7dc0153ddc07455bb929080a1da58403","modified":1634148270166,"created":1634107683373,"url":"localhost:3001/users","name":"createUser","description":"","method":"POST","body":{"mimeType":"application/json","text":"{\n\t\"username\": \"Carl\",\n\t\"password\": \"admin\"\n}"},"parameters":[],"headers":[{"name":"Content-Type","value":"application/json","id":"pair_5877f228e6bd45b5967b71348fd93c7d"}],"authentication":{},"metaSortKey":-1634107683373,"isPrivate":false,"settingStoreCookies":true,"settingSendCookies":true,"settingDisableRenderRequestBody":false,"settingEncodeUrl":true,"settingRebuildPath":true,"settingFollowRedirects":"global","_type":"request"},{"_id":"req_b74dc10aac714c70b28e6947e15e8863","parentId":"fld_7dc0153ddc07455bb929080a1da58403","modified":1634151733037,"created":1634151533921,"url":"localhost:3001/users/616727e7f451d835119b27e2","name":"updateUser","description":"","method":"PUT","body":{"mimeType":"application/json","text":"{\n\t\"username\": \"Erik\",\n\t\"password\": \"admin\"\n}"},"parameters":[],"headers":[{"name":"Content-Type","value":"application/json","id":"pair_2a9b4c017ca047c8b2a0b9ed106cf29c"}],"authentication":{},"metaSortKey":-1634107683323,"isPrivate":false,"settingStoreCookies":true,"settingSendCookies":true,"settingDisableRenderRequestBody":false,"settingEncodeUrl":true,"settingRebuildPath":true,"settingFollowRedirects":"global","_type":"request"},{"_id":"req_5b2841c0a85840a7be1bff82a36e1c1d","parentId":"fld_7dc0153ddc07455bb929080a1da58403","modified":1634152311603,"created":1634152267474,"url":"localhost:3001/users/61672f6b8d3e34500acf9fcd","name":"deleteUser","description":"","method":"DELETE","body":{},"parameters":[],"headers":[],"authentication":{},"metaSortKey":-1633272704159.5,"isPrivate":false,"settingStoreCookies":true,"settingSendCookies":true,"settingDisableRenderRequestBody":false,"settingEncodeUrl":true,"settingRebuildPath":true,"settingFollowRedirects":"global","_type":"request"},{"_id":"env_2782ee78889cf168a3d16915984da783ae1a69e0","parentId":"wrk_97ceffbac6e14947b5bd6594b0364760","modified":1634107657253,"created":1634107657253,"name":"Base Environment","data":{},"dataPropertyOrder":null,"color":null,"isPrivate":false,"metaSortKey":1634107657253,"_type":"environment"},{"_id":"jar_2782ee78889cf168a3d16915984da783ae1a69e0","parentId":"wrk_97ceffbac6e14947b5bd6594b0364760","modified":1634107657255,"created":1634107657255,"name":"Default Jar","cookies":[],"_type":"cookie_jar"},{"_id":"spc_fee887aecb96477098978f0b6b5e553c","parentId":"wrk_97ceffbac6e14947b5bd6594b0364760","modified":1634107657250,"created":1634107657250,"fileName":"API med mongo.yaml","contents":"","contentType":"yaml","_type":"api_spec"}]}